{
  "schema": {
    "fields": [
      "id",
      "term",
      "weight",
      "row_type",
      "row_kind",
      "gloss",
      "provenance"
    ],
    "extended_fields": [
      "status",
      "source_class",
      "voice_lane_fit",
      "aligned_use",
      "unsafe_use",
      "admission_test",
      "provenance_run"
    ],
    "variant_semantics": "independent variants; sizes are not assumed to be nested supersets",
    "row_type_values": [
      "aligned",
      "correlated"
    ],
    "row_kind_values": [
      "noun",
      "phrase",
      "action",
      "thinker",
      "coupling",
      "triplet"
    ],
    "display_contract": "Markdown renders terms only; JSON carries metadata."
  },
  "words": [
    {
      "id": 1,
      "term": "feedback loop",
      "weight": 78,
      "row_type": "aligned",
      "row_kind": "phrase",
      "gloss": "voices:systems cue used inside receipt/probe/status grammar: feedback loop",
      "provenance": "v2.7",
      "status": "candidate",
      "source_class": "technique",
      "voice_lane_fit": "voices:systems",
      "aligned_use": "In voices:systems, use 'feedback loop' only with an explicit probe, receipt, status, or bounded next move.",
      "unsafe_use": "Bare 'feedback loop' as vibe, conclusion, or authority without a probe/receipt/status.",
      "admission_test": "lexical_compaction_v2_7",
      "provenance_run": "codex_refine_wizard_mmm_language_2026-04-28"
    },
    {
      "id": 2,
      "term": "reinforcing loop",
      "weight": 78,
      "row_type": "aligned",
      "row_kind": "phrase",
      "gloss": "voices:systems cue used inside receipt/probe/status grammar: reinforcing loop",
      "provenance": "v2.7",
      "status": "candidate",
      "source_class": "technique",
      "voice_lane_fit": "voices:systems",
      "aligned_use": "In voices:systems, use 'reinforcing loop' only with an explicit probe, receipt, status, or bounded next move.",
      "unsafe_use": "Bare 'reinforcing loop' as vibe, conclusion, or authority without a probe/receipt/status.",
      "admission_test": "lexical_compaction_v2_7",
      "provenance_run": "codex_refine_wizard_mmm_language_2026-04-28"
    },
    {
      "id": 3,
      "term": "balancing loop",
      "weight": 78,
      "row_type": "aligned",
      "row_kind": "phrase",
      "gloss": "voices:systems cue used inside receipt/probe/status grammar: balancing loop",
      "provenance": "v2.7",
      "status": "candidate",
      "source_class": "technique",
      "voice_lane_fit": "voices:systems",
      "aligned_use": "In voices:systems, use 'balancing loop' only with an explicit probe, receipt, status, or bounded next move.",
      "unsafe_use": "Bare 'balancing loop' as vibe, conclusion, or authority without a probe/receipt/status.",
      "admission_test": "lexical_compaction_v2_7",
      "provenance_run": "codex_refine_wizard_mmm_language_2026-04-28"
    },
    {
      "id": 4,
      "term": "system structure",
      "weight": 78,
      "row_type": "aligned",
      "row_kind": "phrase",
      "gloss": "voices:systems cue used inside receipt/probe/status grammar: system structure",
      "provenance": "v2.7",
      "status": "candidate",
      "source_class": "technique",
      "voice_lane_fit": "voices:systems",
      "aligned_use": "In voices:systems, use 'system structure' only with an explicit probe, receipt, status, or bounded next move.",
      "unsafe_use": "Bare 'system structure' as vibe, conclusion, or authority without a probe/receipt/status.",
      "admission_test": "lexical_compaction_v2_7",
      "provenance_run": "codex_refine_wizard_mmm_language_2026-04-28"
    },
    {
      "id": 5,
      "term": "second-order",
      "weight": 78,
      "row_type": "aligned",
      "row_kind": "phrase",
      "gloss": "voices:systems cue used inside receipt/probe/status grammar: second-order",
      "provenance": "v2.7",
      "status": "candidate",
      "source_class": "technique",
      "voice_lane_fit": "voices:systems",
      "aligned_use": "In voices:systems, use 'second-order' only with an explicit probe, receipt, status, or bounded next move.",
      "unsafe_use": "Bare 'second-order' as vibe, conclusion, or authority without a probe/receipt/status.",
      "admission_test": "lexical_compaction_v2_7",
      "provenance_run": "codex_refine_wizard_mmm_language_2026-04-28"
    },
    {
      "id": 6,
      "term": "feedback",
      "weight": 60,
      "row_type": "aligned",
      "row_kind": "noun",
      "gloss": "voices:systems cue used inside receipt/probe/status grammar: feedback",
      "provenance": "v2.7",
      "status": "candidate",
      "source_class": "technique",
      "voice_lane_fit": "voices:systems",
      "aligned_use": "In voices:systems, use 'feedback' only with an explicit probe, receipt, status, or bounded next move.",
      "unsafe_use": "Bare 'feedback' as vibe, conclusion, or authority without a probe/receipt/status.",
      "admission_test": "lexical_compaction_v2_7",
      "provenance_run": "codex_refine_wizard_mmm_language_2026-04-28"
    },
    {
      "id": 7,
      "term": "incentive",
      "weight": 60,
      "row_type": "aligned",
      "row_kind": "noun",
      "gloss": "voices:systems cue used inside receipt/probe/status grammar: incentive",
      "provenance": "v2.7",
      "status": "candidate",
      "source_class": "technique",
      "voice_lane_fit": "voices:systems",
      "aligned_use": "In voices:systems, use 'incentive' only with an explicit probe, receipt, status, or bounded next move.",
      "unsafe_use": "Bare 'incentive' as vibe, conclusion, or authority without a probe/receipt/status.",
      "admission_test": "lexical_compaction_v2_7",
      "provenance_run": "codex_refine_wizard_mmm_language_2026-04-28"
    },
    {
      "id": 8,
      "term": "interaction",
      "weight": 60,
      "row_type": "aligned",
      "row_kind": "noun",
      "gloss": "voices:systems cue used inside receipt/probe/status grammar: interaction",
      "provenance": "v2.7",
      "status": "candidate",
      "source_class": "technique",
      "voice_lane_fit": "voices:systems",
      "aligned_use": "In voices:systems, use 'interaction' only with an explicit probe, receipt, status, or bounded next move.",
      "unsafe_use": "Bare 'interaction' as vibe, conclusion, or authority without a probe/receipt/status.",
      "admission_test": "lexical_compaction_v2_7",
      "provenance_run": "codex_refine_wizard_mmm_language_2026-04-28"
    },
    {
      "id": 9,
      "term": "propagation",
      "weight": 60,
      "row_type": "aligned",
      "row_kind": "noun",
      "gloss": "voices:systems cue used inside receipt/probe/status grammar: propagation",
      "provenance": "v2.7",
      "status": "candidate",
      "source_class": "technique",
      "voice_lane_fit": "voices:systems",
      "aligned_use": "In voices:systems, use 'propagation' only with an explicit probe, receipt, status, or bounded next move.",
      "unsafe_use": "Bare 'propagation' as vibe, conclusion, or authority without a probe/receipt/status.",
      "admission_test": "lexical_compaction_v2_7",
      "provenance_run": "codex_refine_wizard_mmm_language_2026-04-28"
    },
    {
      "id": 10,
      "term": "dependency",
      "weight": 60,
      "row_type": "aligned",
      "row_kind": "noun",
      "gloss": "voices:systems cue used inside receipt/probe/status grammar: dependency",
      "provenance": "v2.7",
      "status": "candidate",
      "source_class": "technique",
      "voice_lane_fit": "voices:systems",
      "aligned_use": "In voices:systems, use 'dependency' only with an explicit probe, receipt, status, or bounded next move.",
      "unsafe_use": "Bare 'dependency' as vibe, conclusion, or authority without a probe/receipt/status.",
      "admission_test": "lexical_compaction_v2_7",
      "provenance_run": "codex_refine_wizard_mmm_language_2026-04-28"
    },
    {
      "id": 11,
      "term": "coupling",
      "weight": 60,
      "row_type": "aligned",
      "row_kind": "action",
      "gloss": "voices:systems cue used inside receipt/probe/status grammar: coupling",
      "provenance": "v2.7",
      "status": "candidate",
      "source_class": "technique",
      "voice_lane_fit": "voices:systems",
      "aligned_use": "In voices:systems, use 'coupling' only with an explicit probe, receipt, status, or bounded next move.",
      "unsafe_use": "Bare 'coupling' as vibe, conclusion, or authority without a probe/receipt/status.",
      "admission_test": "lexical_compaction_v2_7",
      "provenance_run": "codex_refine_wizard_mmm_language_2026-04-28"
    },
    {
      "id": 12,
      "term": "structure",
      "weight": 60,
      "row_type": "aligned",
      "row_kind": "noun",
      "gloss": "voices:systems cue used inside receipt/probe/status grammar: structure",
      "provenance": "v2.7",
      "status": "candidate",
      "source_class": "technique",
      "voice_lane_fit": "voices:systems",
      "aligned_use": "In voices:systems, use 'structure' only with an explicit probe, receipt, status, or bounded next move.",
      "unsafe_use": "Bare 'structure' as vibe, conclusion, or authority without a probe/receipt/status.",
      "admission_test": "lexical_compaction_v2_7",
      "provenance_run": "codex_refine_wizard_mmm_language_2026-04-28"
    },
    {
      "id": 13,
      "term": "loop",
      "weight": 60,
      "row_type": "aligned",
      "row_kind": "noun",
      "gloss": "voices:systems cue used inside receipt/probe/status grammar: loop",
      "provenance": "v2.7",
      "status": "candidate",
      "source_class": "technique",
      "voice_lane_fit": "voices:systems",
      "aligned_use": "In voices:systems, use 'loop' only with an explicit probe, receipt, status, or bounded next move.",
      "unsafe_use": "Bare 'loop' as vibe, conclusion, or authority without a probe/receipt/status.",
      "admission_test": "lexical_compaction_v2_7",
      "provenance_run": "codex_refine_wizard_mmm_language_2026-04-28"
    },
    {
      "id": 14,
      "term": "environment",
      "weight": 60,
      "row_type": "aligned",
      "row_kind": "noun",
      "gloss": "voices:systems cue used inside receipt/probe/status grammar: environment",
      "provenance": "v2.7",
      "status": "candidate",
      "source_class": "technique",
      "voice_lane_fit": "voices:systems",
      "aligned_use": "In voices:systems, use 'environment' only with an explicit probe, receipt, status, or bounded next move.",
      "unsafe_use": "Bare 'environment' as vibe, conclusion, or authority without a probe/receipt/status.",
      "admission_test": "lexical_compaction_v2_7",
      "provenance_run": "codex_refine_wizard_mmm_language_2026-04-28"
    },
    {
      "id": 15,
      "term": "emergence",
      "weight": 60,
      "row_type": "aligned",
      "row_kind": "noun",
      "gloss": "voices:systems cue used inside receipt/probe/status grammar: emergence",
      "provenance": "v2.7",
      "status": "candidate",
      "source_class": "technique",
      "voice_lane_fit": "voices:systems",
      "aligned_use": "In voices:systems, use 'emergence' only with an explicit probe, receipt, status, or bounded next move.",
      "unsafe_use": "Bare 'emergence' as vibe, conclusion, or authority without a probe/receipt/status.",
      "admission_test": "lexical_compaction_v2_7",
      "provenance_run": "codex_refine_wizard_mmm_language_2026-04-28"
    },
    {
      "id": 16,
      "term": "selection",
      "weight": 60,
      "row_type": "aligned",
      "row_kind": "noun",
      "gloss": "voices:systems cue used inside receipt/probe/status grammar: selection",
      "provenance": "v2.7",
      "status": "candidate",
      "source_class": "technique",
      "voice_lane_fit": "voices:systems",
      "aligned_use": "In voices:systems, use 'selection' only with an explicit probe, receipt, status, or bounded next move.",
      "unsafe_use": "Bare 'selection' as vibe, conclusion, or authority without a probe/receipt/status.",
      "admission_test": "lexical_compaction_v2_7",
      "provenance_run": "codex_refine_wizard_mmm_language_2026-04-28"
    },
    {
      "id": 17,
      "term": "network",
      "weight": 60,
      "row_type": "aligned",
      "row_kind": "noun",
      "gloss": "voices:systems cue used inside receipt/probe/status grammar: network",
      "provenance": "v2.7",
      "status": "candidate",
      "source_class": "technique",
      "voice_lane_fit": "voices:systems",
      "aligned_use": "In voices:systems, use 'network' only with an explicit probe, receipt, status, or bounded next move.",
      "unsafe_use": "Bare 'network' as vibe, conclusion, or authority without a probe/receipt/status.",
      "admission_test": "lexical_compaction_v2_7",
      "provenance_run": "codex_refine_wizard_mmm_language_2026-04-28"
    },
    {
      "id": 18,
      "term": "node",
      "weight": 60,
      "row_type": "aligned",
      "row_kind": "noun",
      "gloss": "voices:systems cue used inside receipt/probe/status grammar: node",
      "provenance": "v2.7",
      "status": "candidate",
      "source_class": "technique",
      "voice_lane_fit": "voices:systems",
      "aligned_use": "In voices:systems, use 'node' only with an explicit probe, receipt, status, or bounded next move.",
      "unsafe_use": "Bare 'node' as vibe, conclusion, or authority without a probe/receipt/status.",
      "admission_test": "lexical_compaction_v2_7",
      "provenance_run": "codex_refine_wizard_mmm_language_2026-04-28"
    },
    {
      "id": 19,
      "term": "edge",
      "weight": 60,
      "row_type": "aligned",
      "row_kind": "noun",
      "gloss": "voices:systems cue used inside receipt/probe/status grammar: edge",
      "provenance": "v2.7",
      "status": "candidate",
      "source_class": "technique",
      "voice_lane_fit": "voices:systems",
      "aligned_use": "In voices:systems, use 'edge' only with an explicit probe, receipt, status, or bounded next move.",
      "unsafe_use": "Bare 'edge' as vibe, conclusion, or authority without a probe/receipt/status.",
      "admission_test": "lexical_compaction_v2_7",
      "provenance_run": "codex_refine_wizard_mmm_language_2026-04-28"
    },
    {
      "id": 20,
      "term": "balancing",
      "weight": 60,
      "row_type": "aligned",
      "row_kind": "action",
      "gloss": "voices:systems cue used inside receipt/probe/status grammar: balancing",
      "provenance": "v2.7",
      "status": "candidate",
      "source_class": "technique",
      "voice_lane_fit": "voices:systems",
      "aligned_use": "In voices:systems, use 'balancing' only with an explicit probe, receipt, status, or bounded next move.",
      "unsafe_use": "Bare 'balancing' as vibe, conclusion, or authority without a probe/receipt/status.",
      "admission_test": "lexical_compaction_v2_7",
      "provenance_run": "codex_refine_wizard_mmm_language_2026-04-28"
    },
    {
      "id": 21,
      "term": "reinforcing",
      "weight": 60,
      "row_type": "aligned",
      "row_kind": "action",
      "gloss": "voices:systems cue used inside receipt/probe/status grammar: reinforcing",
      "provenance": "v2.7",
      "status": "candidate",
      "source_class": "technique",
      "voice_lane_fit": "voices:systems",
      "aligned_use": "In voices:systems, use 'reinforcing' only with an explicit probe, receipt, status, or bounded next move.",
      "unsafe_use": "Bare 'reinforcing' as vibe, conclusion, or authority without a probe/receipt/status.",
      "admission_test": "lexical_compaction_v2_7",
      "provenance_run": "codex_refine_wizard_mmm_language_2026-04-28"
    },
    {
      "id": 22,
      "term": "emergent",
      "weight": 60,
      "row_type": "aligned",
      "row_kind": "noun",
      "gloss": "voices:systems cue used inside receipt/probe/status grammar: emergent",
      "provenance": "v2.7",
      "status": "candidate",
      "source_class": "technique",
      "voice_lane_fit": "voices:systems",
      "aligned_use": "In voices:systems, use 'emergent' only with an explicit probe, receipt, status, or bounded next move.",
      "unsafe_use": "Bare 'emergent' as vibe, conclusion, or authority without a probe/receipt/status.",
      "admission_test": "lexical_compaction_v2_7",
      "provenance_run": "codex_refine_wizard_mmm_language_2026-04-28"
    },
    {
      "id": 23,
      "term": "system",
      "weight": 60,
      "row_type": "aligned",
      "row_kind": "noun",
      "gloss": "voices:systems cue used inside receipt/probe/status grammar: system",
      "provenance": "v2.7",
      "status": "candidate",
      "source_class": "technique",
      "voice_lane_fit": "voices:systems",
      "aligned_use": "In voices:systems, use 'system' only with an explicit probe, receipt, status, or bounded next move.",
      "unsafe_use": "Bare 'system' as vibe, conclusion, or authority without a probe/receipt/status.",
      "admission_test": "lexical_compaction_v2_7",
      "provenance_run": "codex_refine_wizard_mmm_language_2026-04-28"
    },
    {
      "id": 24,
      "term": "stock",
      "weight": 60,
      "row_type": "aligned",
      "row_kind": "noun",
      "gloss": "voices:systems cue used inside receipt/probe/status grammar: stock",
      "provenance": "v2.7",
      "status": "candidate",
      "source_class": "technique",
      "voice_lane_fit": "voices:systems",
      "aligned_use": "In voices:systems, use 'stock' only with an explicit probe, receipt, status, or bounded next move.",
      "unsafe_use": "Bare 'stock' as vibe, conclusion, or authority without a probe/receipt/status.",
      "admission_test": "lexical_compaction_v2_7",
      "provenance_run": "codex_refine_wizard_mmm_language_2026-04-28"
    },
    {
      "id": 25,
      "term": "flow",
      "weight": 60,
      "row_type": "aligned",
      "row_kind": "noun",
      "gloss": "voices:systems cue used inside receipt/probe/status grammar: flow",
      "provenance": "v2.7",
      "status": "candidate",
      "source_class": "technique",
      "voice_lane_fit": "voices:systems",
      "aligned_use": "In voices:systems, use 'flow' only with an explicit probe, receipt, status, or bounded next move.",
      "unsafe_use": "Bare 'flow' as vibe, conclusion, or authority without a probe/receipt/status.",
      "admission_test": "lexical_compaction_v2_7",
      "provenance_run": "codex_refine_wizard_mmm_language_2026-04-28"
    },
    {
      "id": 26,
      "term": "delay",
      "weight": 60,
      "row_type": "aligned",
      "row_kind": "noun",
      "gloss": "voices:systems cue used inside receipt/probe/status grammar: delay",
      "provenance": "v2.7",
      "status": "candidate",
      "source_class": "technique",
      "voice_lane_fit": "voices:systems",
      "aligned_use": "In voices:systems, use 'delay' only with an explicit probe, receipt, status, or bounded next move.",
      "unsafe_use": "Bare 'delay' as vibe, conclusion, or authority without a probe/receipt/status.",
      "admission_test": "lexical_compaction_v2_7",
      "provenance_run": "codex_refine_wizard_mmm_language_2026-04-28"
    },
    {
      "id": 27,
      "term": "parameter",
      "weight": 60,
      "row_type": "aligned",
      "row_kind": "noun",
      "gloss": "voices:systems cue used inside receipt/probe/status grammar: parameter",
      "provenance": "v2.7",
      "status": "candidate",
      "source_class": "technique",
      "voice_lane_fit": "voices:systems",
      "aligned_use": "In voices:systems, use 'parameter' only with an explicit probe, receipt, status, or bounded next move.",
      "unsafe_use": "Bare 'parameter' as vibe, conclusion, or authority without a probe/receipt/status.",
      "admission_test": "lexical_compaction_v2_7",
      "provenance_run": "codex_refine_wizard_mmm_language_2026-04-28"
    },
    {
      "id": 28,
      "term": "leverage",
      "weight": 60,
      "row_type": "aligned",
      "row_kind": "noun",
      "gloss": "voices:systems cue used inside receipt/probe/status grammar: leverage",
      "provenance": "v2.7",
      "status": "candidate",
      "source_class": "technique",
      "voice_lane_fit": "voices:systems",
      "aligned_use": "In voices:systems, use 'leverage' only with an explicit probe, receipt, status, or bounded next move.",
      "unsafe_use": "Bare 'leverage' as vibe, conclusion, or authority without a probe/receipt/status.",
      "admission_test": "lexical_compaction_v2_7",
      "provenance_run": "codex_refine_wizard_mmm_language_2026-04-28"
    }
  ],
  "couplings": [
    {
      "id": 1,
      "term": "loop boundary",
      "weight": 92,
      "row_type": "correlated",
      "row_kind": "coupling",
      "gloss": "voices:systems relation phrase that should pull a sentence toward bounded work: loop boundary",
      "provenance": "v2.7",
      "status": "candidate",
      "source_class": "technique",
      "voice_lane_fit": "voices:systems",
      "aligned_use": "In voices:systems, use 'loop boundary' only with an explicit probe, receipt, status, or bounded next move.",
      "unsafe_use": "Bare 'loop boundary' as vibe, conclusion, or authority without a probe/receipt/status.",
      "admission_test": "lexical_compaction_v2_7",
      "provenance_run": "codex_refine_wizard_mmm_language_2026-04-28"
    },
    {
      "id": 2,
      "term": "loop constraint",
      "weight": 92,
      "row_type": "correlated",
      "row_kind": "coupling",
      "gloss": "voices:systems relation phrase that should pull a sentence toward bounded work: loop constraint",
      "provenance": "v2.7",
      "status": "candidate",
      "source_class": "technique",
      "voice_lane_fit": "voices:systems",
      "aligned_use": "In voices:systems, use 'loop constraint' only with an explicit probe, receipt, status, or bounded next move.",
      "unsafe_use": "Bare 'loop constraint' as vibe, conclusion, or authority without a probe/receipt/status.",
      "admission_test": "lexical_compaction_v2_7",
      "provenance_run": "codex_refine_wizard_mmm_language_2026-04-28"
    },
    {
      "id": 3,
      "term": "feedback boundary",
      "weight": 92,
      "row_type": "correlated",
      "row_kind": "coupling",
      "gloss": "voices:systems relation phrase that should pull a sentence toward bounded work: feedback boundary",
      "provenance": "v2.7",
      "status": "candidate",
      "source_class": "technique",
      "voice_lane_fit": "voices:systems",
      "aligned_use": "In voices:systems, use 'feedback boundary' only with an explicit probe, receipt, status, or bounded next move.",
      "unsafe_use": "Bare 'feedback boundary' as vibe, conclusion, or authority without a probe/receipt/status.",
      "admission_test": "lexical_compaction_v2_7",
      "provenance_run": "codex_refine_wizard_mmm_language_2026-04-28"
    },
    {
      "id": 4,
      "term": "feedback constraint",
      "weight": 92,
      "row_type": "correlated",
      "row_kind": "coupling",
      "gloss": "voices:systems relation phrase that should pull a sentence toward bounded work: feedback constraint",
      "provenance": "v2.7",
      "status": "candidate",
      "source_class": "technique",
      "voice_lane_fit": "voices:systems",
      "aligned_use": "In voices:systems, use 'feedback constraint' only with an explicit probe, receipt, status, or bounded next move.",
      "unsafe_use": "Bare 'feedback constraint' as vibe, conclusion, or authority without a probe/receipt/status.",
      "admission_test": "lexical_compaction_v2_7",
      "provenance_run": "codex_refine_wizard_mmm_language_2026-04-28"
    },
    {
      "id": 5,
      "term": "incentive boundary",
      "weight": 92,
      "row_type": "correlated",
      "row_kind": "coupling",
      "gloss": "voices:systems relation phrase that should pull a sentence toward bounded work: incentive boundary",
      "provenance": "v2.7",
      "status": "candidate",
      "source_class": "technique",
      "voice_lane_fit": "voices:systems",
      "aligned_use": "In voices:systems, use 'incentive boundary' only with an explicit probe, receipt, status, or bounded next move.",
      "unsafe_use": "Bare 'incentive boundary' as vibe, conclusion, or authority without a probe/receipt/status.",
      "admission_test": "lexical_compaction_v2_7",
      "provenance_run": "codex_refine_wizard_mmm_language_2026-04-28"
    },
    {
      "id": 6,
      "term": "incentive constraint",
      "weight": 92,
      "row_type": "correlated",
      "row_kind": "coupling",
      "gloss": "voices:systems relation phrase that should pull a sentence toward bounded work: incentive constraint",
      "provenance": "v2.7",
      "status": "candidate",
      "source_class": "technique",
      "voice_lane_fit": "voices:systems",
      "aligned_use": "In voices:systems, use 'incentive constraint' only with an explicit probe, receipt, status, or bounded next move.",
      "unsafe_use": "Bare 'incentive constraint' as vibe, conclusion, or authority without a probe/receipt/status.",
      "admission_test": "lexical_compaction_v2_7",
      "provenance_run": "codex_refine_wizard_mmm_language_2026-04-28"
    },
    {
      "id": 7,
      "term": "structure boundary",
      "weight": 92,
      "row_type": "correlated",
      "row_kind": "coupling",
      "gloss": "voices:systems relation phrase that should pull a sentence toward bounded work: structure boundary",
      "provenance": "v2.7",
      "status": "candidate",
      "source_class": "technique",
      "voice_lane_fit": "voices:systems",
      "aligned_use": "In voices:systems, use 'structure boundary' only with an explicit probe, receipt, status, or bounded next move.",
      "unsafe_use": "Bare 'structure boundary' as vibe, conclusion, or authority without a probe/receipt/status.",
      "admission_test": "lexical_compaction_v2_7",
      "provenance_run": "codex_refine_wizard_mmm_language_2026-04-28"
    },
    {
      "id": 8,
      "term": "structure constraint",
      "weight": 92,
      "row_type": "correlated",
      "row_kind": "coupling",
      "gloss": "voices:systems relation phrase that should pull a sentence toward bounded work: structure constraint",
      "provenance": "v2.7",
      "status": "candidate",
      "source_class": "technique",
      "voice_lane_fit": "voices:systems",
      "aligned_use": "In voices:systems, use 'structure constraint' only with an explicit probe, receipt, status, or bounded next move.",
      "unsafe_use": "Bare 'structure constraint' as vibe, conclusion, or authority without a probe/receipt/status.",
      "admission_test": "lexical_compaction_v2_7",
      "provenance_run": "codex_refine_wizard_mmm_language_2026-04-28"
    },
    {
      "id": 9,
      "term": "interaction boundary",
      "weight": 92,
      "row_type": "correlated",
      "row_kind": "coupling",
      "gloss": "voices:systems relation phrase that should pull a sentence toward bounded work: interaction boundary",
      "provenance": "v2.7",
      "status": "candidate",
      "source_class": "technique",
      "voice_lane_fit": "voices:systems",
      "aligned_use": "In voices:systems, use 'interaction boundary' only with an explicit probe, receipt, status, or bounded next move.",
      "unsafe_use": "Bare 'interaction boundary' as vibe, conclusion, or authority without a probe/receipt/status.",
      "admission_test": "lexical_compaction_v2_7",
      "provenance_run": "codex_refine_wizard_mmm_language_2026-04-28"
    },
    {
      "id": 10,
      "term": "interaction constraint",
      "weight": 92,
      "row_type": "correlated",
      "row_kind": "coupling",
      "gloss": "voices:systems relation phrase that should pull a sentence toward bounded work: interaction constraint",
      "provenance": "v2.7",
      "status": "candidate",
      "source_class": "technique",
      "voice_lane_fit": "voices:systems",
      "aligned_use": "In voices:systems, use 'interaction constraint' only with an explicit probe, receipt, status, or bounded next move.",
      "unsafe_use": "Bare 'interaction constraint' as vibe, conclusion, or authority without a probe/receipt/status.",
      "admission_test": "lexical_compaction_v2_7",
      "provenance_run": "codex_refine_wizard_mmm_language_2026-04-28"
    },
    {
      "id": 11,
      "term": "propagation boundary",
      "weight": 92,
      "row_type": "correlated",
      "row_kind": "coupling",
      "gloss": "voices:systems relation phrase that should pull a sentence toward bounded work: propagation boundary",
      "provenance": "v2.7",
      "status": "candidate",
      "source_class": "technique",
      "voice_lane_fit": "voices:systems",
      "aligned_use": "In voices:systems, use 'propagation boundary' only with an explicit probe, receipt, status, or bounded next move.",
      "unsafe_use": "Bare 'propagation boundary' as vibe, conclusion, or authority without a probe/receipt/status.",
      "admission_test": "lexical_compaction_v2_7",
      "provenance_run": "codex_refine_wizard_mmm_language_2026-04-28"
    },
    {
      "id": 12,
      "term": "propagation constraint",
      "weight": 92,
      "row_type": "correlated",
      "row_kind": "coupling",
      "gloss": "voices:systems relation phrase that should pull a sentence toward bounded work: propagation constraint",
      "provenance": "v2.7",
      "status": "candidate",
      "source_class": "technique",
      "voice_lane_fit": "voices:systems",
      "aligned_use": "In voices:systems, use 'propagation constraint' only with an explicit probe, receipt, status, or bounded next move.",
      "unsafe_use": "Bare 'propagation constraint' as vibe, conclusion, or authority without a probe/receipt/status.",
      "admission_test": "lexical_compaction_v2_7",
      "provenance_run": "codex_refine_wizard_mmm_language_2026-04-28"
    },
    {
      "id": 13,
      "term": "coupling boundary",
      "weight": 92,
      "row_type": "correlated",
      "row_kind": "coupling",
      "gloss": "voices:systems relation phrase that should pull a sentence toward bounded work: coupling boundary",
      "provenance": "v2.7",
      "status": "candidate",
      "source_class": "technique",
      "voice_lane_fit": "voices:systems",
      "aligned_use": "In voices:systems, use 'coupling boundary' only with an explicit probe, receipt, status, or bounded next move.",
      "unsafe_use": "Bare 'coupling boundary' as vibe, conclusion, or authority without a probe/receipt/status.",
      "admission_test": "lexical_compaction_v2_7",
      "provenance_run": "codex_refine_wizard_mmm_language_2026-04-28"
    },
    {
      "id": 14,
      "term": "coupling constraint",
      "weight": 92,
      "row_type": "correlated",
      "row_kind": "coupling",
      "gloss": "voices:systems relation phrase that should pull a sentence toward bounded work: coupling constraint",
      "provenance": "v2.7",
      "status": "candidate",
      "source_class": "technique",
      "voice_lane_fit": "voices:systems",
      "aligned_use": "In voices:systems, use 'coupling constraint' only with an explicit probe, receipt, status, or bounded next move.",
      "unsafe_use": "Bare 'coupling constraint' as vibe, conclusion, or authority without a probe/receipt/status.",
      "admission_test": "lexical_compaction_v2_7",
      "provenance_run": "codex_refine_wizard_mmm_language_2026-04-28"
    },
    {
      "id": 15,
      "term": "feedback loop",
      "weight": 92,
      "row_type": "correlated",
      "row_kind": "coupling",
      "gloss": "voices:systems relation phrase that should pull a sentence toward bounded work: feedback loop",
      "provenance": "v2.7",
      "status": "candidate",
      "source_class": "technique",
      "voice_lane_fit": "voices:systems",
      "aligned_use": "In voices:systems, use 'feedback loop' only with an explicit probe, receipt, status, or bounded next move.",
      "unsafe_use": "Bare 'feedback loop' as vibe, conclusion, or authority without a probe/receipt/status.",
      "admission_test": "lexical_compaction_v2_7",
      "provenance_run": "codex_refine_wizard_mmm_language_2026-04-28"
    },
    {
      "id": 16,
      "term": "reinforcing loop",
      "weight": 92,
      "row_type": "correlated",
      "row_kind": "coupling",
      "gloss": "voices:systems relation phrase that should pull a sentence toward bounded work: reinforcing loop",
      "provenance": "v2.7",
      "status": "candidate",
      "source_class": "technique",
      "voice_lane_fit": "voices:systems",
      "aligned_use": "In voices:systems, use 'reinforcing loop' only with an explicit probe, receipt, status, or bounded next move.",
      "unsafe_use": "Bare 'reinforcing loop' as vibe, conclusion, or authority without a probe/receipt/status.",
      "admission_test": "lexical_compaction_v2_7",
      "provenance_run": "codex_refine_wizard_mmm_language_2026-04-28"
    },
    {
      "id": 17,
      "term": "balancing loop",
      "weight": 92,
      "row_type": "correlated",
      "row_kind": "coupling",
      "gloss": "voices:systems relation phrase that should pull a sentence toward bounded work: balancing loop",
      "provenance": "v2.7",
      "status": "candidate",
      "source_class": "technique",
      "voice_lane_fit": "voices:systems",
      "aligned_use": "In voices:systems, use 'balancing loop' only with an explicit probe, receipt, status, or bounded next move.",
      "unsafe_use": "Bare 'balancing loop' as vibe, conclusion, or authority without a probe/receipt/status.",
      "admission_test": "lexical_compaction_v2_7",
      "provenance_run": "codex_refine_wizard_mmm_language_2026-04-28"
    },
    {
      "id": 18,
      "term": "loop evidence",
      "weight": 92,
      "row_type": "correlated",
      "row_kind": "coupling",
      "gloss": "voices:systems relation phrase that should pull a sentence toward bounded work: loop evidence",
      "provenance": "v2.7",
      "status": "candidate",
      "source_class": "technique",
      "voice_lane_fit": "voices:systems",
      "aligned_use": "In voices:systems, use 'loop evidence' only with an explicit probe, receipt, status, or bounded next move.",
      "unsafe_use": "Bare 'loop evidence' as vibe, conclusion, or authority without a probe/receipt/status.",
      "admission_test": "lexical_compaction_v2_7",
      "provenance_run": "codex_refine_wizard_mmm_language_2026-04-28"
    },
    {
      "id": 19,
      "term": "loop support",
      "weight": 92,
      "row_type": "correlated",
      "row_kind": "coupling",
      "gloss": "voices:systems relation phrase that should pull a sentence toward bounded work: loop support",
      "provenance": "v2.7",
      "status": "candidate",
      "source_class": "technique",
      "voice_lane_fit": "voices:systems",
      "aligned_use": "In voices:systems, use 'loop support' only with an explicit probe, receipt, status, or bounded next move.",
      "unsafe_use": "Bare 'loop support' as vibe, conclusion, or authority without a probe/receipt/status.",
      "admission_test": "lexical_compaction_v2_7",
      "provenance_run": "codex_refine_wizard_mmm_language_2026-04-28"
    },
    {
      "id": 20,
      "term": "loop packet",
      "weight": 92,
      "row_type": "correlated",
      "row_kind": "coupling",
      "gloss": "voices:systems relation phrase that should pull a sentence toward bounded work: loop packet",
      "provenance": "v2.7",
      "status": "candidate",
      "source_class": "technique",
      "voice_lane_fit": "voices:systems",
      "aligned_use": "In voices:systems, use 'loop packet' only with an explicit probe, receipt, status, or bounded next move.",
      "unsafe_use": "Bare 'loop packet' as vibe, conclusion, or authority without a probe/receipt/status.",
      "admission_test": "lexical_compaction_v2_7",
      "provenance_run": "codex_refine_wizard_mmm_language_2026-04-28"
    },
    {
      "id": 21,
      "term": "loop receipt",
      "weight": 92,
      "row_type": "correlated",
      "row_kind": "coupling",
      "gloss": "voices:systems relation phrase that should pull a sentence toward bounded work: loop receipt",
      "provenance": "v2.7",
      "status": "candidate",
      "source_class": "technique",
      "voice_lane_fit": "voices:systems",
      "aligned_use": "In voices:systems, use 'loop receipt' only with an explicit probe, receipt, status, or bounded next move.",
      "unsafe_use": "Bare 'loop receipt' as vibe, conclusion, or authority without a probe/receipt/status.",
      "admission_test": "lexical_compaction_v2_7",
      "provenance_run": "codex_refine_wizard_mmm_language_2026-04-28"
    },
    {
      "id": 22,
      "term": "loop trace",
      "weight": 92,
      "row_type": "correlated",
      "row_kind": "coupling",
      "gloss": "voices:systems relation phrase that should pull a sentence toward bounded work: loop trace",
      "provenance": "v2.7",
      "status": "candidate",
      "source_class": "technique",
      "voice_lane_fit": "voices:systems",
      "aligned_use": "In voices:systems, use 'loop trace' only with an explicit probe, receipt, status, or bounded next move.",
      "unsafe_use": "Bare 'loop trace' as vibe, conclusion, or authority without a probe/receipt/status.",
      "admission_test": "lexical_compaction_v2_7",
      "provenance_run": "codex_refine_wizard_mmm_language_2026-04-28"
    },
    {
      "id": 23,
      "term": "loop result",
      "weight": 92,
      "row_type": "correlated",
      "row_kind": "coupling",
      "gloss": "voices:systems relation phrase that should pull a sentence toward bounded work: loop result",
      "provenance": "v2.7",
      "status": "candidate",
      "source_class": "technique",
      "voice_lane_fit": "voices:systems",
      "aligned_use": "In voices:systems, use 'loop result' only with an explicit probe, receipt, status, or bounded next move.",
      "unsafe_use": "Bare 'loop result' as vibe, conclusion, or authority without a probe/receipt/status.",
      "admission_test": "lexical_compaction_v2_7",
      "provenance_run": "codex_refine_wizard_mmm_language_2026-04-28"
    },
    {
      "id": 24,
      "term": "loop scope",
      "weight": 92,
      "row_type": "correlated",
      "row_kind": "coupling",
      "gloss": "voices:systems relation phrase that should pull a sentence toward bounded work: loop scope",
      "provenance": "v2.7",
      "status": "candidate",
      "source_class": "technique",
      "voice_lane_fit": "voices:systems",
      "aligned_use": "In voices:systems, use 'loop scope' only with an explicit probe, receipt, status, or bounded next move.",
      "unsafe_use": "Bare 'loop scope' as vibe, conclusion, or authority without a probe/receipt/status.",
      "admission_test": "lexical_compaction_v2_7",
      "provenance_run": "codex_refine_wizard_mmm_language_2026-04-28"
    },
    {
      "id": 25,
      "term": "loop witness",
      "weight": 92,
      "row_type": "correlated",
      "row_kind": "coupling",
      "gloss": "voices:systems relation phrase that should pull a sentence toward bounded work: loop witness",
      "provenance": "v2.7",
      "status": "candidate",
      "source_class": "technique",
      "voice_lane_fit": "voices:systems",
      "aligned_use": "In voices:systems, use 'loop witness' only with an explicit probe, receipt, status, or bounded next move.",
      "unsafe_use": "Bare 'loop witness' as vibe, conclusion, or authority without a probe/receipt/status.",
      "admission_test": "lexical_compaction_v2_7",
      "provenance_run": "codex_refine_wizard_mmm_language_2026-04-28"
    },
    {
      "id": 26,
      "term": "loop probe",
      "weight": 92,
      "row_type": "correlated",
      "row_kind": "coupling",
      "gloss": "voices:systems relation phrase that should pull a sentence toward bounded work: loop probe",
      "provenance": "v2.7",
      "status": "candidate",
      "source_class": "technique",
      "voice_lane_fit": "voices:systems",
      "aligned_use": "In voices:systems, use 'loop probe' only with an explicit probe, receipt, status, or bounded next move.",
      "unsafe_use": "Bare 'loop probe' as vibe, conclusion, or authority without a probe/receipt/status.",
      "admission_test": "lexical_compaction_v2_7",
      "provenance_run": "codex_refine_wizard_mmm_language_2026-04-28"
    },
    {
      "id": 27,
      "term": "compare loop",
      "weight": 92,
      "row_type": "correlated",
      "row_kind": "coupling",
      "gloss": "voices:systems relation phrase that should pull a sentence toward bounded work: compare loop",
      "provenance": "v2.7",
      "status": "candidate",
      "source_class": "technique",
      "voice_lane_fit": "voices:systems",
      "aligned_use": "In voices:systems, use 'compare loop' only with an explicit probe, receipt, status, or bounded next move.",
      "unsafe_use": "Bare 'compare loop' as vibe, conclusion, or authority without a probe/receipt/status.",
      "admission_test": "lexical_compaction_v2_7",
      "provenance_run": "codex_refine_wizard_mmm_language_2026-04-28"
    },
    {
      "id": 28,
      "term": "measure loop",
      "weight": 92,
      "row_type": "correlated",
      "row_kind": "coupling",
      "gloss": "voices:systems relation phrase that should pull a sentence toward bounded work: measure loop",
      "provenance": "v2.7",
      "status": "candidate",
      "source_class": "technique",
      "voice_lane_fit": "voices:systems",
      "aligned_use": "In voices:systems, use 'measure loop' only with an explicit probe, receipt, status, or bounded next move.",
      "unsafe_use": "Bare 'measure loop' as vibe, conclusion, or authority without a probe/receipt/status.",
      "admission_test": "lexical_compaction_v2_7",
      "provenance_run": "codex_refine_wizard_mmm_language_2026-04-28"
    },
    {
      "id": 29,
      "term": "positive feedback",
      "weight": 92,
      "row_type": "correlated",
      "row_kind": "coupling",
      "gloss": "voices:systems relation phrase that should pull a sentence toward bounded work: positive feedback",
      "provenance": "v2.7",
      "status": "candidate",
      "source_class": "technique",
      "voice_lane_fit": "voices:systems",
      "aligned_use": "In voices:systems, use 'positive feedback' only with an explicit probe, receipt, status, or bounded next move.",
      "unsafe_use": "Bare 'positive feedback' as vibe, conclusion, or authority without a probe/receipt/status.",
      "admission_test": "lexical_compaction_v2_7",
      "provenance_run": "codex_refine_wizard_mmm_language_2026-04-28"
    },
    {
      "id": 30,
      "term": "stock and flow",
      "weight": 92,
      "row_type": "correlated",
      "row_kind": "coupling",
      "gloss": "voices:systems relation phrase that should pull a sentence toward bounded work: stock and flow",
      "provenance": "v2.7",
      "status": "candidate",
      "source_class": "technique",
      "voice_lane_fit": "voices:systems",
      "aligned_use": "In voices:systems, use 'stock and flow' only with an explicit probe, receipt, status, or bounded next move.",
      "unsafe_use": "Bare 'stock and flow' as vibe, conclusion, or authority without a probe/receipt/status.",
      "admission_test": "lexical_compaction_v2_7",
      "provenance_run": "codex_refine_wizard_mmm_language_2026-04-28"
    },
    {
      "id": 31,
      "term": "information flow",
      "weight": 92,
      "row_type": "correlated",
      "row_kind": "coupling",
      "gloss": "voices:systems relation phrase that should pull a sentence toward bounded work: information flow",
      "provenance": "v2.7",
      "status": "candidate",
      "source_class": "technique",
      "voice_lane_fit": "voices:systems",
      "aligned_use": "In voices:systems, use 'information flow' only with an explicit probe, receipt, status, or bounded next move.",
      "unsafe_use": "Bare 'information flow' as vibe, conclusion, or authority without a probe/receipt/status.",
      "admission_test": "lexical_compaction_v2_7",
      "provenance_run": "codex_refine_wizard_mmm_language_2026-04-28"
    },
    {
      "id": 32,
      "term": "loop",
      "weight": 89,
      "row_type": "correlated",
      "row_kind": "coupling",
      "gloss": "voices:systems relation phrase that should pull a sentence toward bounded work: loop",
      "provenance": "v2.7",
      "status": "candidate",
      "source_class": "technique",
      "voice_lane_fit": "voices:systems",
      "aligned_use": "In voices:systems, use 'loop' only with an explicit probe, receipt, status, or bounded next move.",
      "unsafe_use": "Bare 'loop' as vibe, conclusion, or authority without a probe/receipt/status.",
      "admission_test": "lexical_compaction_v2_7",
      "provenance_run": "codex_refine_wizard_mmm_language_2026-04-28"
    },
    {
      "id": 33,
      "term": "feedback",
      "weight": 89,
      "row_type": "correlated",
      "row_kind": "coupling",
      "gloss": "voices:systems relation phrase that should pull a sentence toward bounded work: feedback",
      "provenance": "v2.7",
      "status": "candidate",
      "source_class": "technique",
      "voice_lane_fit": "voices:systems",
      "aligned_use": "In voices:systems, use 'feedback' only with an explicit probe, receipt, status, or bounded next move.",
      "unsafe_use": "Bare 'feedback' as vibe, conclusion, or authority without a probe/receipt/status.",
      "admission_test": "lexical_compaction_v2_7",
      "provenance_run": "codex_refine_wizard_mmm_language_2026-04-28"
    },
    {
      "id": 34,
      "term": "coupling",
      "weight": 89,
      "row_type": "correlated",
      "row_kind": "coupling",
      "gloss": "voices:systems relation phrase that should pull a sentence toward bounded work: coupling",
      "provenance": "v2.7",
      "status": "candidate",
      "source_class": "technique",
      "voice_lane_fit": "voices:systems",
      "aligned_use": "In voices:systems, use 'coupling' only with an explicit probe, receipt, status, or bounded next move.",
      "unsafe_use": "Bare 'coupling' as vibe, conclusion, or authority without a probe/receipt/status.",
      "admission_test": "lexical_compaction_v2_7",
      "provenance_run": "codex_refine_wizard_mmm_language_2026-04-28"
    },
    {
      "id": 35,
      "term": "propagation",
      "weight": 89,
      "row_type": "correlated",
      "row_kind": "coupling",
      "gloss": "voices:systems relation phrase that should pull a sentence toward bounded work: propagation",
      "provenance": "v2.7",
      "status": "candidate",
      "source_class": "technique",
      "voice_lane_fit": "voices:systems",
      "aligned_use": "In voices:systems, use 'propagation' only with an explicit probe, receipt, status, or bounded next move.",
      "unsafe_use": "Bare 'propagation' as vibe, conclusion, or authority without a probe/receipt/status.",
      "admission_test": "lexical_compaction_v2_7",
      "provenance_run": "codex_refine_wizard_mmm_language_2026-04-28"
    },
    {
      "id": 36,
      "term": "incentive",
      "weight": 89,
      "row_type": "correlated",
      "row_kind": "coupling",
      "gloss": "voices:systems relation phrase that should pull a sentence toward bounded work: incentive",
      "provenance": "v2.7",
      "status": "candidate",
      "source_class": "technique",
      "voice_lane_fit": "voices:systems",
      "aligned_use": "In voices:systems, use 'incentive' only with an explicit probe, receipt, status, or bounded next move.",
      "unsafe_use": "Bare 'incentive' as vibe, conclusion, or authority without a probe/receipt/status.",
      "admission_test": "lexical_compaction_v2_7",
      "provenance_run": "codex_refine_wizard_mmm_language_2026-04-28"
    },
    {
      "id": 37,
      "term": "structure",
      "weight": 89,
      "row_type": "correlated",
      "row_kind": "coupling",
      "gloss": "voices:systems relation phrase that should pull a sentence toward bounded work: structure",
      "provenance": "v2.7",
      "status": "candidate",
      "source_class": "technique",
      "voice_lane_fit": "voices:systems",
      "aligned_use": "In voices:systems, use 'structure' only with an explicit probe, receipt, status, or bounded next move.",
      "unsafe_use": "Bare 'structure' as vibe, conclusion, or authority without a probe/receipt/status.",
      "admission_test": "lexical_compaction_v2_7",
      "provenance_run": "codex_refine_wizard_mmm_language_2026-04-28"
    },
    {
      "id": 38,
      "term": "dependency",
      "weight": 89,
      "row_type": "correlated",
      "row_kind": "coupling",
      "gloss": "voices:systems relation phrase that should pull a sentence toward bounded work: dependency",
      "provenance": "v2.7",
      "status": "candidate",
      "source_class": "technique",
      "voice_lane_fit": "voices:systems",
      "aligned_use": "In voices:systems, use 'dependency' only with an explicit probe, receipt, status, or bounded next move.",
      "unsafe_use": "Bare 'dependency' as vibe, conclusion, or authority without a probe/receipt/status.",
      "admission_test": "lexical_compaction_v2_7",
      "provenance_run": "codex_refine_wizard_mmm_language_2026-04-28"
    },
    {
      "id": 39,
      "term": "interaction",
      "weight": 89,
      "row_type": "correlated",
      "row_kind": "coupling",
      "gloss": "voices:systems relation phrase that should pull a sentence toward bounded work: interaction",
      "provenance": "v2.7",
      "status": "candidate",
      "source_class": "technique",
      "voice_lane_fit": "voices:systems",
      "aligned_use": "In voices:systems, use 'interaction' only with an explicit probe, receipt, status, or bounded next move.",
      "unsafe_use": "Bare 'interaction' as vibe, conclusion, or authority without a probe/receipt/status.",
      "admission_test": "lexical_compaction_v2_7",
      "provenance_run": "codex_refine_wizard_mmm_language_2026-04-28"
    }
  ],
  "triplets": [
    {
      "id": 1,
      "term": "stock flow feedback",
      "weight": 86,
      "row_type": "correlated",
      "row_kind": "triplet",
      "gloss": "voices:systems cadence for keeping three-part reasoning aligned: stock flow feedback",
      "provenance": "v2.7",
      "status": "candidate",
      "source_class": "technique",
      "voice_lane_fit": "voices:systems",
      "aligned_use": "In voices:systems, use 'stock flow feedback' only with an explicit probe, receipt, status, or bounded next move.",
      "unsafe_use": "Bare 'stock flow feedback' as vibe, conclusion, or authority without a probe/receipt/status.",
      "admission_test": "lexical_compaction_v2_7",
      "provenance_run": "codex_refine_wizard_mmm_language_2026-04-28"
    },
    {
      "id": 2,
      "term": "goal rule incentive",
      "weight": 86,
      "row_type": "correlated",
      "row_kind": "triplet",
      "gloss": "voices:systems cadence for keeping three-part reasoning aligned: goal rule incentive",
      "provenance": "v2.7",
      "status": "candidate",
      "source_class": "technique",
      "voice_lane_fit": "voices:systems",
      "aligned_use": "In voices:systems, use 'goal rule incentive' only with an explicit probe, receipt, status, or bounded next move.",
      "unsafe_use": "Bare 'goal rule incentive' as vibe, conclusion, or authority without a probe/receipt/status.",
      "admission_test": "lexical_compaction_v2_7",
      "provenance_run": "codex_refine_wizard_mmm_language_2026-04-28"
    },
    {
      "id": 3,
      "term": "loop delay response",
      "weight": 86,
      "row_type": "correlated",
      "row_kind": "triplet",
      "gloss": "voices:systems cadence for keeping three-part reasoning aligned: loop delay response",
      "provenance": "v2.7",
      "status": "candidate",
      "source_class": "technique",
      "voice_lane_fit": "voices:systems",
      "aligned_use": "In voices:systems, use 'loop delay response' only with an explicit probe, receipt, status, or bounded next move.",
      "unsafe_use": "Bare 'loop delay response' as vibe, conclusion, or authority without a probe/receipt/status.",
      "admission_test": "lexical_compaction_v2_7",
      "provenance_run": "codex_refine_wizard_mmm_language_2026-04-28"
    },
    {
      "id": 4,
      "term": "system boundary coupling",
      "weight": 86,
      "row_type": "correlated",
      "row_kind": "triplet",
      "gloss": "voices:systems cadence for keeping three-part reasoning aligned: system boundary coupling",
      "provenance": "v2.7",
      "status": "candidate",
      "source_class": "technique",
      "voice_lane_fit": "voices:systems",
      "aligned_use": "In voices:systems, use 'system boundary coupling' only with an explicit probe, receipt, status, or bounded next move.",
      "unsafe_use": "Bare 'system boundary coupling' as vibe, conclusion, or authority without a probe/receipt/status.",
      "admission_test": "lexical_compaction_v2_7",
      "provenance_run": "codex_refine_wizard_mmm_language_2026-04-28"
    },
    {
      "id": 5,
      "term": "leverage point intervention",
      "weight": 86,
      "row_type": "correlated",
      "row_kind": "triplet",
      "gloss": "voices:systems cadence for keeping three-part reasoning aligned: leverage point intervention",
      "provenance": "v2.7",
      "status": "candidate",
      "source_class": "technique",
      "voice_lane_fit": "voices:systems",
      "aligned_use": "In voices:systems, use 'leverage point intervention' only with an explicit probe, receipt, status, or bounded next move.",
      "unsafe_use": "Bare 'leverage point intervention' as vibe, conclusion, or authority without a probe/receipt/status.",
      "admission_test": "lexical_compaction_v2_7",
      "provenance_run": "codex_refine_wizard_mmm_language_2026-04-28"
    },
    {
      "id": 6,
      "term": "information flow access",
      "weight": 86,
      "row_type": "correlated",
      "row_kind": "triplet",
      "gloss": "voices:systems cadence for keeping three-part reasoning aligned: information flow access",
      "provenance": "v2.7",
      "status": "candidate",
      "source_class": "technique",
      "voice_lane_fit": "voices:systems",
      "aligned_use": "In voices:systems, use 'information flow access' only with an explicit probe, receipt, status, or bounded next move.",
      "unsafe_use": "Bare 'information flow access' as vibe, conclusion, or authority without a probe/receipt/status.",
      "admission_test": "lexical_compaction_v2_7",
      "provenance_run": "codex_refine_wizard_mmm_language_2026-04-28"
    },
    {
      "id": 7,
      "term": "positive feedback growth",
      "weight": 86,
      "row_type": "correlated",
      "row_kind": "triplet",
      "gloss": "voices:systems cadence for keeping three-part reasoning aligned: positive feedback growth",
      "provenance": "v2.7",
      "status": "candidate",
      "source_class": "technique",
      "voice_lane_fit": "voices:systems",
      "aligned_use": "In voices:systems, use 'positive feedback growth' only with an explicit probe, receipt, status, or bounded next move.",
      "unsafe_use": "Bare 'positive feedback growth' as vibe, conclusion, or authority without a probe/receipt/status.",
      "admission_test": "lexical_compaction_v2_7",
      "provenance_run": "codex_refine_wizard_mmm_language_2026-04-28"
    },
    {
      "id": 8,
      "term": "second order effect",
      "weight": 86,
      "row_type": "correlated",
      "row_kind": "triplet",
      "gloss": "voices:systems cadence for keeping three-part reasoning aligned: second order effect",
      "provenance": "v2.7",
      "status": "candidate",
      "source_class": "technique",
      "voice_lane_fit": "voices:systems",
      "aligned_use": "In voices:systems, use 'second order effect' only with an explicit probe, receipt, status, or bounded next move.",
      "unsafe_use": "Bare 'second order effect' as vibe, conclusion, or authority without a probe/receipt/status.",
      "admission_test": "lexical_compaction_v2_7",
      "provenance_run": "codex_refine_wizard_mmm_language_2026-04-28"
    },
    {
      "id": 9,
      "term": "emergent behavior pattern",
      "weight": 86,
      "row_type": "correlated",
      "row_kind": "triplet",
      "gloss": "voices:systems cadence for keeping three-part reasoning aligned: emergent behavior pattern",
      "provenance": "v2.7",
      "status": "candidate",
      "source_class": "technique",
      "voice_lane_fit": "voices:systems",
      "aligned_use": "In voices:systems, use 'emergent behavior pattern' only with an explicit probe, receipt, status, or bounded next move.",
      "unsafe_use": "Bare 'emergent behavior pattern' as vibe, conclusion, or authority without a probe/receipt/status.",
      "admission_test": "lexical_compaction_v2_7",
      "provenance_run": "codex_refine_wizard_mmm_language_2026-04-28"
    },
    {
      "id": 10,
      "term": "self organization structure",
      "weight": 86,
      "row_type": "correlated",
      "row_kind": "triplet",
      "gloss": "voices:systems cadence for keeping three-part reasoning aligned: self organization structure",
      "provenance": "v2.7",
      "status": "candidate",
      "source_class": "technique",
      "voice_lane_fit": "voices:systems",
      "aligned_use": "In voices:systems, use 'self organization structure' only with an explicit probe, receipt, status, or bounded next move.",
      "unsafe_use": "Bare 'self organization structure' as vibe, conclusion, or authority without a probe/receipt/status.",
      "admission_test": "lexical_compaction_v2_7",
      "provenance_run": "codex_refine_wizard_mmm_language_2026-04-28"
    },
    {
      "id": 11,
      "term": "rules goals paradigm",
      "weight": 86,
      "row_type": "correlated",
      "row_kind": "triplet",
      "gloss": "voices:systems cadence for keeping three-part reasoning aligned: rules goals paradigm",
      "provenance": "v2.7",
      "status": "candidate",
      "source_class": "technique",
      "voice_lane_fit": "voices:systems",
      "aligned_use": "In voices:systems, use 'rules goals paradigm' only with an explicit probe, receipt, status, or bounded next move.",
      "unsafe_use": "Bare 'rules goals paradigm' as vibe, conclusion, or authority without a probe/receipt/status.",
      "admission_test": "lexical_compaction_v2_7",
      "provenance_run": "codex_refine_wizard_mmm_language_2026-04-28"
    },
    {
      "id": 12,
      "term": "incentive selection pressure",
      "weight": 86,
      "row_type": "correlated",
      "row_kind": "triplet",
      "gloss": "voices:systems cadence for keeping three-part reasoning aligned: incentive selection pressure",
      "provenance": "v2.7",
      "status": "candidate",
      "source_class": "technique",
      "voice_lane_fit": "voices:systems",
      "aligned_use": "In voices:systems, use 'incentive selection pressure' only with an explicit probe, receipt, status, or bounded next move.",
      "unsafe_use": "Bare 'incentive selection pressure' as vibe, conclusion, or authority without a probe/receipt/status.",
      "admission_test": "lexical_compaction_v2_7",
      "provenance_run": "codex_refine_wizard_mmm_language_2026-04-28"
    }
  ]
}
